gr_urchin/__init__.py
gr_urchin/urdf.py
gr_urchin/utils.py
gr_urchin/version.py
gr_urchin-0.0.29.dist-info/LICENSE
gr_urchin-0.0.29.dist-info/METADATA
gr_urchin-0.0.29.dist-info/WHEEL
gr_urchin-0.0.29.dist-info/top_level.txt
gr_urchin-0.0.29.dist-info/RECORD
